Metadata-Version: 2.1
Name: lco-bpm-maker
Version: 0.2.0
Summary: LCO bad pixel mask creator
Home-page: https://github.com/LCOGT/pixel-mask-gen
Author: Matt Daily
Author-email: mdaily@lco.global
License: UNKNOWN
Platform: UNKNOWN
